<?xml version="1.0" encoding="utf-8" ?>
<dwsync>
<file name="index.html" server="gcsfinancialcorp.com" local="133301123082187832" remote="133240125000000000" Dst="2" />
<file name="Loan_solution_model.php" server="gcsfinancialcorp.com" local="133301122770227482" remote="133252156200000000" Dst="2" />
<file name="We_serve_model.php" server="gcsfinancialcorp.com" local="133301122772540431" remote="133252203000000000" Dst="2" />
<file name="Apply_onilne_model.php" server="gcsfinancialcorp.com" local="133249098712683017" remote="133300078200000000" Dst="2" />
<file name="About_us_model.php" server="gcsfinancialcorp.com" local="133301122762550500" remote="133251531000000000" Dst="2" />
<file name="Blog_model.php" server="gcsfinancialcorp.com" local="133301122766689214" remote="133248769800000000" Dst="2" />
<file name="Contact_us_model.php" server="gcsfinancialcorp.com" local="133301122767476405" remote="133251531000000000" Dst="2" />
<file name="Home_model.php" server="gcsfinancialcorp.com" local="133301122769615115" remote="133268648400000000" Dst="2" />
<file name="Privacy_policy_model.php" server="gcsfinancialcorp.com" local="133301122772161363" remote="133276401000000000" Dst="2" />
</dwsync>