<?xml version="1.0" encoding="utf-8" ?>
<dwsync>
<file name="baseball.svg" server="gcsfinancialcorp.com" local="133301121942279314" remote="133240281000000000" Dst="2" />
<file name="coupon.svg" server="gcsfinancialcorp.com" local="133301121944342420" remote="133240281000000000" Dst="2" />
<file name="coupon1.svg" server="gcsfinancialcorp.com" local="133301121944928423" remote="133240281000000000" Dst="2" />
<file name="discount.svg" server="gcsfinancialcorp.com" local="133301121945149353" remote="133240281000000000" Dst="2" />
<file name="festival.svg" server="gcsfinancialcorp.com" local="133301121947407546" remote="133240281000000000" Dst="2" />
<file name="gift-card.svg" server="gcsfinancialcorp.com" local="133301121948021580" remote="133240281000000000" Dst="2" />
<file name="interview.svg" server="gcsfinancialcorp.com" local="133301121948220384" remote="133240281000000000" Dst="2" />
<file name="medal-bronze.svg" server="gcsfinancialcorp.com" local="133301121950610380" remote="133240281000000000" Dst="2" />
<file name="medal-gold.svg" server="gcsfinancialcorp.com" local="133301121950590395" remote="133240281000000000" Dst="2" />
<file name="medal-platinum.svg" server="gcsfinancialcorp.com" local="133301121951017597" remote="133240281000000000" Dst="2" />
<file name="medal-silver.svg" server="gcsfinancialcorp.com" local="133301121953180786" remote="133240281000000000" Dst="2" />
<file name="medal-trial.svg" server="gcsfinancialcorp.com" local="133301121953767347" remote="133240281000000000" Dst="2" />
<file name="voucher.svg" server="gcsfinancialcorp.com" local="133301121953767347" remote="133240281000000000" Dst="2" />
</dwsync>