<?xml version="1.0" encoding="utf-8" ?>
<dwsync>
<file name="CodeIgniter.php" server="transportarlogistics.com" local="132907873090000000" remote="133240222200000000" Dst="0" />
<file name="Benchmark.php" server="transportarlogistics.com" local="132907873090000000" remote="133240222200000000" Dst="0" />
<file name="Common.php" server="transportarlogistics.com" local="132907873090000000" remote="133240222200000000" Dst="0" />
<file name="Config.php" server="transportarlogistics.com" local="132907873090000000" remote="133240222200000000" Dst="0" />
<file name="Controller.php" server="transportarlogistics.com" local="132907873090000000" remote="133240222200000000" Dst="0" />
<file name="Exceptions.php" server="transportarlogistics.com" local="132907873090000000" remote="133240222200000000" Dst="0" />
<file name="Hooks.php" server="transportarlogistics.com" local="132907873090000000" remote="133240222200000000" Dst="0" />
<file name="index.html" server="transportarlogistics.com" local="132907873090000000" remote="133240222200000000" Dst="0" />
<file name="Input.php" server="transportarlogistics.com" local="132907873090000000" remote="133240222200000000" Dst="0" />
<file name="Lang.php" server="transportarlogistics.com" local="132907873090000000" remote="133240222200000000" Dst="0" />
<file name="Loader.php" server="transportarlogistics.com" local="132907873090000000" remote="133240222200000000" Dst="0" />
<file name="Log.php" server="transportarlogistics.com" local="132907873090000000" remote="133240222200000000" Dst="0" />
<file name="Model.php" server="transportarlogistics.com" local="132907873090000000" remote="133240222200000000" Dst="0" />
<file name="Output.php" server="transportarlogistics.com" local="132907873090000000" remote="133240222200000000" Dst="0" />
<file name="Router.php" server="transportarlogistics.com" local="132907873090000000" remote="133240222200000000" Dst="0" />
<file name="Security.php" server="transportarlogistics.com" local="132907873090000000" remote="133240222200000000" Dst="0" />
<file name="URI.php" server="transportarlogistics.com" local="132907873090000000" remote="133240222200000000" Dst="0" />
<file name="Utf8.php" server="transportarlogistics.com" local="132907873090000000" remote="133240222200000000" Dst="0" />
<file name="Benchmark.php" server="gcsfinancialcorp.com" local="133301122362970509" remote="133240155000000000" Dst="2" />
<file name="Common.php" server="gcsfinancialcorp.com" local="133301122365544362" remote="133240155000000000" Dst="2" />
<file name="CodeIgniter.php" server="gcsfinancialcorp.com" local="133301122363641167" remote="133240155000000000" Dst="2" />
<file name="Config.php" server="gcsfinancialcorp.com" local="133301122365730800" remote="133240155000000000" Dst="2" />
<file name="Controller.php" server="gcsfinancialcorp.com" local="133301122366645221" remote="133240155000000000" Dst="2" />
<file name="Hooks.php" server="gcsfinancialcorp.com" local="133301122368500647" remote="133240155000000000" Dst="2" />
<file name="Exceptions.php" server="gcsfinancialcorp.com" local="133301122368129076" remote="133240155000000000" Dst="2" />
<file name="index.html" server="gcsfinancialcorp.com" local="133301122385997650" remote="133240155000000000" Dst="2" />
<file name="Input.php" server="gcsfinancialcorp.com" local="133301122369982579" remote="133240155000000000" Dst="2" />
<file name="Lang.php" server="gcsfinancialcorp.com" local="133301122371336503" remote="133240155000000000" Dst="2" />
<file name="Loader.php" server="gcsfinancialcorp.com" local="133301122372304875" remote="133240155000000000" Dst="2" />
<file name="Model.php" server="gcsfinancialcorp.com" local="133301122374402307" remote="133240155000000000" Dst="2" />
<file name="Log.php" server="gcsfinancialcorp.com" local="133301122373210775" remote="133240155000000000" Dst="2" />
<file name="Output.php" server="gcsfinancialcorp.com" local="133301122375859223" remote="133240155000000000" Dst="2" />
<file name="Router.php" server="gcsfinancialcorp.com" local="133301122376553279" remote="133240155000000000" Dst="2" />
<file name="URI.php" server="gcsfinancialcorp.com" local="133301122379568094" remote="133240155000000000" Dst="2" />
<file name="Security.php" server="gcsfinancialcorp.com" local="133301122378088416" remote="133240155000000000" Dst="2" />
<file name="Utf8.php" server="gcsfinancialcorp.com" local="133301122379732120" remote="133240155000000000" Dst="2" />
</dwsync>