<?xml version="1.0" encoding="utf-8" ?>
<dwsync>
<file name="index.html" server="transportarlogistics.com" local="132907873090000000" remote="133240222200000000" Dst="0" />
<file name="oci8_driver.php" server="transportarlogistics.com" local="132907873090000000" remote="133240222200000000" Dst="0" />
<file name="oci8_forge.php" server="transportarlogistics.com" local="132907873090000000" remote="133240222200000000" Dst="0" />
<file name="oci8_result.php" server="transportarlogistics.com" local="132907873090000000" remote="133240222200000000" Dst="0" />
<file name="oci8_utility.php" server="transportarlogistics.com" local="132907873090000000" remote="133240222200000000" Dst="0" />
<file name="index.html" server="gcsfinancialcorp.com" local="133301122422203008" remote="133240155000000000" Dst="2" />
<file name="oci8_driver.php" server="gcsfinancialcorp.com" local="133301122423709691" remote="133240155000000000" Dst="2" />
<file name="oci8_forge.php" server="gcsfinancialcorp.com" local="133301122424671441" remote="133240155000000000" Dst="2" />
<file name="oci8_utility.php" server="gcsfinancialcorp.com" local="133301122427118107" remote="133240155000000000" Dst="2" />
<file name="oci8_result.php" server="gcsfinancialcorp.com" local="133301122425323214" remote="133240155000000000" Dst="2" />
</dwsync>